MANIFEST.in
README.rst
setup.py
plone/__init__.py
plone.app.layoutpage.egg-info/PKG-INFO
plone.app.layoutpage.egg-info/SOURCES.txt
plone.app.layoutpage.egg-info/dependency_links.txt
plone.app.layoutpage.egg-info/entry_points.txt
plone.app.layoutpage.egg-info/namespace_packages.txt
plone.app.layoutpage.egg-info/not-zip-safe
plone.app.layoutpage.egg-info/requires.txt
plone.app.layoutpage.egg-info/top_level.txt
plone/app/__init__.py
plone/app/layoutpage/__init__.py
plone/app/layoutpage/configure.zcml
plone/app/layoutpage/interfaces.py
plone/app/layoutpage/testing.py
plone/app/layoutpage/browser/__init__.py
plone/app/layoutpage/browser/page.py
plone/app/layoutpage/browser/templates/page.html
plone/app/layoutpage/browser/templates/page.pt
plone/app/layoutpage/images/page_icon.gif
plone/app/layoutpage/profiles/default/metadata.xml
plone/app/layoutpage/profiles/default/propertiestool.xml
plone/app/layoutpage/profiles/default/types.xml
plone/app/layoutpage/profiles/default/types/page.xml
plone/app/layoutpage/tests/__init__.py
plone/app/layoutpage/tests/test_content.py