Metadata-Version: 1.1
Name: plone.app.layoutpage
Version: 1.1
Summary: A basic page content type for Plone using Deco layout
Home-page: http://github.com/plone/plone.app.layoutpage
Author: David Glick
Author-email: dglick@gmail.com
License: GPL
Platform: UNKNOWN
Classifier: Framework :: Plone
Classifier: Programming Language :: Python
Classifier: Topic :: Software Development :: Libraries :: Python Modules
